{
  "apprenant": [
    {
      "name": "Hala Ziani",
      "id": 1
    },
    {
      "name": "Faiza Rabhi",
      "id": 2
    },
    {
      "name": "c",
      "id": 3
    },
    {
      "name": "D",
      "id": 4
    },
    {
      "name": "KAMAL",
      "id": 5
    },
    {
      "name": "mohammed",
      "id": 6
    },
    {
      "name": "amine",
      "id": 7
    },
    {
      "name": "",
      "id": 8
    },
    {
      "name": "Fatimaezahrae aitlsri",
      "id": 9
    },
    {
      "name": "Abdelah Atguiri",
      "id": 10
    }
  ]
}